pycryption.py
pycryption-1.0.0.dist-info/WHEEL
pycryption-1.0.0.dist-info/METADATA
pycryption-1.0.0.dist-info/RECORD
